tik_device_generator/__init__.py
tik_device_generator/generator.py
tik_device_generator-0.1.0.dist-info/METADATA
tik_device_generator-0.1.0.dist-info/WHEEL
tik_device_generator-0.1.0.dist-info/top_level.txt
tik_device_generator-0.1.0.dist-info/RECORD
