Metadata-Version: 2.4
Name: tik_device_generator
Version: 0.1.0
Summary: A library to generate TikTok device information.
Home-page: https://github.com/yourusername/tik_device_generator
Author: S1
Author-email: your.email@example.com
Classifier: Programming Language :: Python :: 3
Classifier: License :: OSI Approved :: MIT License
Classifier: Operating System :: OS Independent
Requires-Python: >=3.6
Requires-Dist: requests
Requires-Dist: SignerPy
Dynamic: author
Dynamic: author-email
Dynamic: classifier
Dynamic: description
Dynamic: description-content-type
Dynamic: home-page
Dynamic: requires-dist
Dynamic: requires-python
Dynamic: summary
